pbc_distance_calculator/__init__.py
pbc_distance_calculator/calculator.py
pbc_distance_calculator/checks.py
pbc_distance_calculator/utils/__init__.py
pbc_distance_calculator-1.3.3.dist-info/LICENSE
pbc_distance_calculator-1.3.3.dist-info/METADATA
pbc_distance_calculator-1.3.3.dist-info/WHEEL
pbc_distance_calculator-1.3.3.dist-info/top_level.txt
pbc_distance_calculator-1.3.3.dist-info/RECORD
