Metadata-Version: 2.1
Name: pbc_distance_calculator
Version: 1.3.3
Summary: A package for computing distances accounting for periodic boundary conditions
Home-page: https://github.com/muexly/pbc_distance_calculator
Author: Jacob Jeffries
Author-email: jwjeffr@clemson.edu
License: MIT
Keywords: periodic-boundary-conditions,distance-computation,simulation,molecular-dynamics,lattice-systems,neighbor-lists,periodic-images
Requires-Python: <=3.12,>=3.8
License-File: LICENSE
Requires-Dist: numpy
